llm_file_format-0.1.1.dist-info/METADATA
llm_file_format-0.1.1.dist-info/WHEEL
llm_file_format-0.1.1.dist-info/entry_points.txt
llm_file_format-0.1.1.dist-info/licenses/LICENSE
llm_fmt/__init__.py
llm_fmt/_native.cpython-314-aarch64-linux-gnu.so
llm_fmt/cli.py
llm_fmt/config.py
llm_fmt/py.typed
llm_file_format-0.1.1.dist-info/RECORD
