Metadata-Version: 2.4
Name: llm-file-format
Version: 0.1.1
Classifier: Development Status :: 4 - Beta
Classifier: Environment :: Console
Classifier: Intended Audience :: Developers
Classifier: License :: OSI Approved :: MIT License
Classifier: Operating System :: OS Independent
Classifier: Programming Language :: Python :: 3
Classifier: Programming Language :: Python :: 3.10
Classifier: Programming Language :: Python :: 3.11
Classifier: Programming Language :: Python :: 3.12
Classifier: Programming Language :: Python :: 3.13
Classifier: Programming Language :: Python :: 3.14
Classifier: Programming Language :: Rust
Classifier: Topic :: Software Development :: Libraries :: Python Modules
Classifier: Topic :: Text Processing :: General
Classifier: Topic :: Scientific/Engineering :: Artificial Intelligence
Classifier: Typing :: Typed
Requires-Dist: click~=8.1
Requires-Dist: pyyaml~=6.0
License-File: LICENSE
Summary: Token-efficient data format converter for LLM contexts
Keywords: llm,tokens,json,toon,yaml,ai,agents,context,compression,format,converter
Author: SerPeter
License: MIT
Requires-Python: >=3.10
Project-URL: Changelog, https://github.com/SerPeter/llm-fmt-project/releases
Project-URL: Documentation, https://github.com/SerPeter/llm-fmt-project#readme
Project-URL: Homepage, https://github.com/SerPeter/llm-fmt-project
Project-URL: Issues, https://github.com/SerPeter/llm-fmt-project/issues
Project-URL: Repository, https://github.com/SerPeter/llm-fmt-project
